netscan_rp-0.1.2.dist-info/METADATA
netscan_rp-0.1.2.dist-info/WHEEL
netscan_rp/__init__.py
netscan_rp/netscan_rp.cp39-win_amd64.pyd
netscan_rp-0.1.2.dist-info/RECORD
