Metadata-Version: 2.1
Name: netscan_rp
Version: 0.1.2
Classifier: Programming Language :: Rust
Classifier: Programming Language :: Python :: Implementation :: CPython
Classifier: Programming Language :: Python :: Implementation :: PyPy
Classifier: License :: OSI Approved :: MIT License 
Summary: A Network Scan Libray based in Rust qscan
Keywords: network,scanner,pentest,qscan,port,scan
Author: Luka Oliveira
Author-email: pedrolukaoliveira@protonmail.com
Requires-Python: >=3.7
Project-URL: homepage, https://github.com/LukaOliveira/netscan_rp
Project-URL: repository, https://github.com/LukaOliveira/netscan_rp
Project-URL: documentation, https://github.com/LukaOliveira/netscan_rp
